llama_index/readers/notion/__init__.py
llama_index/readers/notion/base.py
llama_index_readers_notion-0.4.0.dist-info/METADATA
llama_index_readers_notion-0.4.0.dist-info/WHEEL
llama_index_readers_notion-0.4.0.dist-info/licenses/LICENSE
llama_index_readers_notion-0.4.0.dist-info/RECORD
