Metadata-Version: 2.4
Name: llama-index-readers-notion
Version: 0.4.0
Summary: llama-index readers notion integration
Author-email: Your Name <you@example.com>
Maintainer: jerryjliu
License-Expression: MIT
License-File: LICENSE
Requires-Python: <4.0,>=3.9
Requires-Dist: llama-index-core<0.14,>=0.13.0
